ddam/__init__.py
ddam/as_helper.py
ddam/data.py
ddam/exabgp_conf.py
ddam/metrics.py
ddam/smtp.py
ddam/state.py
ddam/templates/blackhole_email.txt.j2
ddam/templates/exabgp.conf.j2
ddam/templates/unblackhole_email.txt.j2
ddam-1.4.4.dist-info/LICENSE
ddam-1.4.4.dist-info/METADATA
ddam-1.4.4.dist-info/WHEEL
ddam-1.4.4.dist-info/entry_points.txt
ddam-1.4.4.dist-info/RECORD
