Metadata-Version: 2.3
Name: ddam
Version: 1.4.4
Summary: 
Author: Sergej Alikov
Author-email: sergej@alikov.com
Requires-Python: >=3.13,<4.0
Classifier: Programming Language :: Python :: 3
Classifier: Programming Language :: Python :: 3.13
Requires-Dist: elasticsearch (>=8.17.2,<9.0.0)
Requires-Dist: exabgp (>=4.2.25,<5.0.0)
Requires-Dist: fastapi (>=0.115.12,<0.116.0)
Requires-Dist: jinja2 (>=3.1.6,<4.0.0)
Requires-Dist: prometheus-client (>=0.21.1,<0.22.0)
Requires-Dist: requests (>=2.32.3,<3.0.0)
Requires-Dist: uvicorn (>=0.34.2,<0.35.0)
